kombo/__init__.py
kombo/_version.py
kombo/assessment.py
kombo/ats.py
kombo/basesdk.py
kombo/connect.py
kombo/general.py
kombo/hris.py
kombo/httpclient.py
kombo/py.typed
kombo/sdk.py
kombo/sdkconfiguration.py
kombo/_hooks/__init__.py
kombo/_hooks/registration.py
kombo/_hooks/sdkhooks.py
kombo/_hooks/types.py
kombo/errors/__init__.py
kombo/errors/komboatserror.py
kombo/errors/kombogeneralerror.py
kombo/errors/kombohriserror.py
kombo/errors/no_response_error.py
kombo/errors/responsevalidationerror.py
kombo/errors/sdkdefaulterror.py
kombo/errors/sdkerror.py
kombo/models/__init__.py
kombo/models/assessmentorderreceivedwebhookpayload.py
kombo/models/connectionflowfailedwebhookpayload.py
kombo/models/datachangedwebhookpayload.py
kombo/models/deleteatscandidatescandidateidtagsop.py
kombo/models/deleteatscandidatescandidateidtagspositiveresponse.py
kombo/models/deleteatscandidatescandidateidtagsrequestbody.py
kombo/models/deletehrisabsencesabsenceidop.py
kombo/models/deletehrisabsencesabsenceidpositiveresponse.py
kombo/models/deletehrisabsencesabsenceidrequestbody.py
kombo/models/deleteintegrationsintegrationidop.py
kombo/models/deleteintegrationsintegrationidpositiveresponse.py
kombo/models/deleteintegrationsintegrationidrequestbody.py
kombo/models/getassessmentordersopenop.py
kombo/models/getassessmentordersopenpositiveresponse.py
kombo/models/getassessmentpackagesop.py
kombo/models/getassessmentpackagespositiveresponse.py
kombo/models/getatsapplicationsapplicationidattachmentsop.py
kombo/models/getatsapplicationsapplicationidattachmentspositiveresponse.py
kombo/models/getatsapplicationsop.py
kombo/models/getatsapplicationspositiveresponse.py
kombo/models/getatsapplicationstagesop.py
kombo/models/getatsapplicationstagespositiveresponse.py
kombo/models/getatscandidatescandidateidattachmentsop.py
kombo/models/getatscandidatescandidateidattachmentspositiveresponse.py
kombo/models/getatscandidatesop.py
kombo/models/getatscandidatespositiveresponse.py
kombo-0.2.3.dist-info/METADATA
kombo-0.2.3.dist-info/WHEEL
kombo-0.2.3.dist-info/top_level.txt
kombo-0.2.3.dist-info/RECORD
